{"questions":[{"id":-1,"sourcePath":"anno 2070","lastAnswer":"?","onlySeries":false,"tipps":["?","Wurde in Deutschland entwickelt","Genre: Aufbausimulation / Strategiespiel"],"actualTipLevel":0,"unlocked":false},{"id":-1,"sourcePath":"anthem","lastAnswer":"?","onlySeries":false,"tipps":["?","Genre: Action-Rollenspiel, Shooter","Kam Anfang 2019 von BioWare und EA als Publisher"],"actualTipLevel":0,"unlocked":false},{"id":-1,"sourcePath":"ark survival evolved","lastAnswer":"?","onlySeries":false,"tipps":["?","Genre: Action-Survival-Adventure","Hier müssen Dinosaurier gezähmt werden"],"actualTipLevel":0,"unlocked":false},{"id":-1,"sourcePath":"army of two","lastAnswer":"?","onlySeries":false,"tipps":["?","Genre: Third-Person Shooter","Zeichnet sich dadurch aus, dass dieses Spiel im Co-op Modus gespielt wird"],"actualTipLevel":0,"unlocked":false},{"id":-1,"sourcePath":"assassins creed 2","lastAnswer":"?","onlySeries":false,"tipps":["?","Genre: Action-Adventure, Open World, Stealth","Desmond Miles"],"actualTipLevel":0,"unlocked":false},{"id":-1,"sourcePath":"banjo kazooie","lastAnswer":"?","onlySeries":false,"tipps":["?","Ein Klassiker auf dem Nintendo 64","Man spielt das Duo bestehend aus Bären und Vogel"],"actualTipLevel":0,"unlocked":false},{"id":-1,"sourcePath":"battlefield","lastAnswer":"?","onlySeries":false,"tipps":["?","Genre: Ego-Shooter, Kriegssimulation","Ein Spiel entwickelt von DICE und von EA gepublisht"],"actualTipLevel":0,"unlocked":false},{"id":-1,"sourcePath":"borderlands","lastAnswer":"?","onlySeries":false,"tipps":["?","Spiel in einer Apokalyptischen frei-erkundbaren Welt.","Man hat die Auswahl zwischen mehreren Klassen mit unterschiedlichen Fähigkeiten"],"actualTipLevel":0,"unlocked":false},{"id":-1,"sourcePath":"chrono trigger","lastAnswer":"?","onlySeries":false,"tipps":["?","Ein Klassiker von Square Enix auf dem Super Nintendo","Im Spiel reist man durch die Zeit"],"actualTipLevel":0,"unlocked":false},{"id":-1,"sourcePath":"crysis","lastAnswer":"?","onlySeries":true,"tipps":["?","Genre: Ego-Shooter","Wurde mit der CryEngine entwickelt"],"actualTipLevel":0,"unlocked":false},{"id":-1,"sourcePath":"destiny","lastAnswer":"?","onlySeries":true,"tipps":["?","Der erste Teil der Reihe erschien im August 2017","Der Spieler spielt einen Hüter, der einen Reisenden vor Außerirdischen verteidigt"],"actualTipLevel":0,"unlocked":false},{"id":-1,"sourcePath":"diablo","lastAnswer":"?","onlySeries":true,"tipps":["?","Genre: Action-Rollenspiel, Hack and Slay","Ein Spiel über Dämonen und Engel von Blizzard Entertainment"],"actualTipLevel":0,"unlocked":false},{"id":-1,"sourcePath":"dungeon defenders","lastAnswer":"?","onlySeries":true,"tipps":["?","Genre: Tower Defense","Ein 3D Tower Defense Spiel in dem der Spieler selbst auch zur Waffe greift"],"actualTipLevel":0,"unlocked":false},{"id":-1,"sourcePath":"fall guys","lastAnswer":"?","onlySeries":false,"tipps":["?","Genre: Battle Royale","Ein 'Takeshis Castle' mal mit Kapselförmigen Spielfiguren"],"actualTipLevel":0,"unlocked":false},{"id":-1,"sourcePath":"fat princess","lastAnswer":"?","onlySeries":false,"tipps":["?","Eine Prinzessin, die auch mal mit dem Nachbarn einen Krieg beginnt um weiteren Kuchen zu bekommen","Im Spiel selbst müssen wir unsere Prinzessin aus der Feindlichen Burg befreien und zurück bringen"],"actualTipLevel":0,"unlocked":false},{"id":-1,"sourcePath":"genesis","lastAnswer":"?","onlySeries":true,"tipps":["?","Genre: Free2Play-MOBA","Wurde von Rampage Games entwickelt"],"actualTipLevel":0,"unlocked":false},{"id":-1,"sourcePath":"genshin impact","lastAnswer":"?","onlySeries":false,"tipps":["?","Sieht aus wie The Legend of Zelda Breath of the wild","Der Spieler kann mit einer Gruppe aus bis zu 4 Kämpfern die Welt erkunden"],"actualTipLevel":0,"unlocked":false},{"id":-1,"sourcePath":"halo","lastAnswer":"?","onlySeries":false,"tipps":["?","Ein Ego-Shooter auf einem riesigem Ring im Weltall","Master Chief"],"actualTipLevel":0,"unlocked":false},{"id":-1,"sourcePath":"hearthstone","lastAnswer":"?","onlySeries":true,"tipps":["?","Online Kartenspiel","Von Blizzard Entertainment entwickelt"],"actualTipLevel":0,"unlocked":false},{"id":-1,"sourcePath":"heavy rain","lastAnswer":"?","onlySeries":false,"tipps":["?","Das Cover des Spiels zeigt eine Origami Figur","Die spielbaren Charaktere sind: Ethan Mars, Madison Paige, Norman Jayden und Scott Shelby"],"actualTipLevel":0,"unlocked":false},{"id":-1,"sourcePath":"heroes of might and magic","lastAnswer":"?","onlySeries":true,"tipps":["?","Ein rundenbasiertes Strategiespiel","Die wählbaren Völker tragen Namen wie: Schloss, Schutzwall, Turm oder Inferno"],"actualTipLevel":0,"unlocked":false},{"id":-1,"sourcePath":"hollow knight","lastAnswer":"?","onlySeries":false,"tipps":["?","Die spielwelt wird hauptsächlich von aufrecht gehenden Insekten bevölkert","Die Handlung spielt im gefallenen Königreich Heilandsnest"],"actualTipLevel":0,"unlocked":false},{"id":-1,"sourcePath":"horizon zero dawn","lastAnswer":"?","onlySeries":false,"tipps":["?","Ein open-world Spiel in einer postapokalyptischen Zukunft","Man spielt die Jägerin Aloy vom Stamm der Nora"],"actualTipLevel":0,"unlocked":false},{"id":-1,"sourcePath":"i am setsuna","lastAnswer":"?","onlySeries":false,"tipps":["?","ein klassisches Rollenspiel, welches im anfang 2016 erschien","Die Geschichte handelt um die Reise eines Opfers in einer zum größten Teil Schneelandschaft"],"actualTipLevel":0,"unlocked":false},{"id":-1,"sourcePath":"kingdom hearts","lastAnswer":"?","onlySeries":false,"tipps":["?","Ein Spiel mit Disney Charakteren","Der Hauptcharakter kämpft mit einem großen Schlüssel als Waffe"],"actualTipLevel":0,"unlocked":false},{"id":-1,"sourcePath":"life is strange","lastAnswer":"?","onlySeries":false,"tipps":["?","Man spielt aus der Sicht von Maxine Caulfield","Die Handlung spielt in der Stadt Arcadia Bay"],"actualTipLevel":0,"unlocked":false},{"id":-1,"sourcePath":"little big planet","lastAnswer":"?","onlySeries":true,"tipps":["?","Ein buntes Adventure aus der Sicht einer Stoffpuppe","Der Hauptcharakter wird auch Sackboy genannt"],"actualTipLevel":0,"unlocked":false},{"id":-1,"sourcePath":"mario kart 64","lastAnswer":"?","onlySeries":false,"tipps":["?","Hier sind Charaktere wie Mario, Bowser oder Todd zu finden","Ein Rennspiel für den Nintendo 64"],"actualTipLevel":0,"unlocked":false},{"id":-1,"sourcePath":"might and magic","lastAnswer":"?","onlySeries":true,"tipps":["?","Ein Puzzle-Rollenspiel-Adventure","3 gleiche Figuren hintereinander bilden einen stärkeren Angriff, 3 gleiche Figuren nebeneinander eine Mauer"],"actualTipLevel":0,"unlocked":false},{"id":-1,"sourcePath":"okami","lastAnswer":"?","onlySeries":false,"tipps":["?","Man spielt als Sonnengöttin Amaterasu","Das Ziel ist die Welt vom finsteren Dämon Orochi zu befreien"],"actualTipLevel":0,"unlocked":false},{"id":-1,"sourcePath":"orcs must die","lastAnswer":"?","onlySeries":false,"tipps":["?","Hier müssen Fallen aufgestellt werden um Orcs zu vernichten","Der Hauptcharakter heißt Maximilian im Nachfolger können aber auch andere Charaktere gespielt werden"],"actualTipLevel":0,"unlocked":false},{"id":-1,"sourcePath":"overwatch","lastAnswer":"?","onlySeries":true,"tipps":["?","Ein Mehrspieler Ego-Shooter mit Fähigkeiten","Wählbare Helden sind beispielsweise Mercy, Reinhardt oder Roadhog"],"actualTipLevel":0,"unlocked":false},{"id":-1,"sourcePath":"pixeljunk monsters","lastAnswer":"?","onlySeries":true,"tipps":["?","Ein Tower Defense Spiel","Türme werden hier aus Bäumen gebaut"],"actualTipLevel":0,"unlocked":false},{"id":-1,"sourcePath":"rocket league","lastAnswer":"?","onlySeries":false,"tipps":["?","2 Teams versuchen einen riesigen Ball ins gegnerische Tor zu befördern","Das Spielprinzip ähnelt am ehesten einem Autoballspiel"],"actualTipLevel":0,"unlocked":false},{"id":-1,"sourcePath":"socom ii","lastAnswer":"?","onlySeries":false,"tipps":["?","Der genaue Titel wird mit einer römischen zwei geschrieben: II","Ein Online-Taktik-Shooter für die Playstation 2"],"actualTipLevel":0,"unlocked":false},{"id":-1,"sourcePath":"star fox 64","lastAnswer":"?","onlySeries":false,"tipps":["?","Hier spielt man einen Fuchs","Das Spiel ist ein Klassiker auf dem Nintendo 64"],"actualTipLevel":0,"unlocked":false},{"id":-1,"sourcePath":"star wars battlefront","lastAnswer":"?","onlySeries":true,"tipps":["?","Ein Ego-Shooter von EA mit Weltraumschlachten","Spielbare Helden sind unter anderem Luke Skywalker oder Darth Vader"],"actualTipLevel":0,"unlocked":false},{"id":-1,"sourcePath":"super mario 64","lastAnswer":"?","onlySeries":false,"tipps":["?","Ein Klassiker auf dem Nintendo 64","Der Hauptcharakter ist ein dicker Klempner"],"actualTipLevel":0,"unlocked":false},{"id":-1,"sourcePath":"super smash bros.","lastAnswer":"?","onlySeries":true,"tipps":["?","Hier sind die bekanntesten Spielfiguren von Nintendo vertreten","Ein Nintendo Prügel-Spiel"],"actualTipLevel":0,"unlocked":false},{"id":-1,"sourcePath":"supreme commander","lastAnswer":"?","onlySeries":true,"tipps":["?","Ein Echtzeit-Strategiespiel","Wählbare Völker sind Cybran, UEF und Aeon"],"actualTipLevel":0,"unlocked":false},{"id":-1,"sourcePath":"swords of ditto","lastAnswer":"?","onlySeries":false,"tipps":["?","Ein Action-RPG","Man kämpft mit Spielzeugwaffen gegen den Bösewicht Mormo"],"actualTipLevel":0,"unlocked":false},{"id":-1,"sourcePath":"the division","lastAnswer":"?","onlySeries":true,"tipps":["?","Ein Third-Person Loot-Shooter von Ubisoft","Ein Virus namens Dollar-Grippe bricht in New York City aus"],"actualTipLevel":0,"unlocked":false},{"id":-1,"sourcePath":"the last of us","lastAnswer":"?","onlySeries":true,"tipps":["?","Rund 60 Prozent der Weltbefölkerung sind mit einem mutierten Cordyceps-Pilz infiziert","Der Spieler erlebt die Geschichte aus den Perspektiven von Joel und Ellie"],"actualTipLevel":0,"unlocked":false},{"id":-1,"sourcePath":"the legend of zelda","lastAnswer":"?","onlySeries":true,"tipps":["?","Man spielt einen kleinen Waisenjunge, der im Wald lebt.","Die Fee in diesem Teil des Spiels heißt Navi"],"actualTipLevel":0,"unlocked":false},{"id":-1,"sourcePath":"undertale","lastAnswer":"?","onlySeries":false,"tipps":["?","Über das Reich der Unterwelt regieren König Asgore und Königin Toriel","Während dieser Melodie bekämpft man den Boss Sans"],"actualTipLevel":0,"unlocked":false},{"id":-1,"sourcePath":"xenoblade chronicles","lastAnswer":"?","onlySeries":true,"tipps":["?","Die Story spielt auf zwei riesigen Kriegern mit dem Namen Bionis und Mechonis","Der Hauptcharakter trägt den Namen Shulk"],"actualTipLevel":0,"unlocked":false},{"id":-1,"sourcePath":"yoshis story","lastAnswer":"?","onlySeries":true,"tipps":["?","Der Spieler spielt einen kleinen Dinosaurier, der mit Eiern werfen kann","Der Nachfolger von Super Mario World 2: Yoshis Island"],"actualTipLevel":0,"unlocked":false}]}